{"width":2048,"imagePath":"monero_tex.png","height":4096,"name":"monero","SubTexture":[{"width":157,"y":3125,"height":451,"name":"monero/jacketback","x":1737},{"width":291,"y":3799,"height":236,"name":"monero/hairbask","x":1},{"width":222,"y":1,"height":258,"name":"monero/arm-right","x":1643},{"width":218,"y":261,"height":260,"name":"monero/lacketsleeve-right","x":1643},{"width":424,"y":1,"height":2161,"name":"monero/body","x":1},{"width":238,"y":3724,"height":317,"name":"monero/head","x":687},{"width":140,"y":4043,"height":28,"name":"monero/eyeball","x":687},{"width":114,"y":4073,"height":17,"name":"monero/iris","x":1},{"width":177,"y":3663,"height":74,"name":"monero/eyelids","x":1403},{"width":44,"y":3724,"height":60,"name":"monero/mouth-nose","x":927},{"width":371,"y":2164,"height":1633,"name":"monero/darkleg-right","x":1},{"width":313,"y":2164,"height":1551,"name":"monero/leftleg","x":374},{"width":197,"y":523,"height":201,"name":"monero/shoe-right","x":1643},{"width":308,"y":2164,"height":1558,"name":"monero/darkleg-left","x":689},{"width":177,"y":523,"height":204,"name":"monero/shoe-left","x":1842},{"width":289,"y":3927,"height":161,"name":"monero/pants","x":927},{"width":316,"y":3740,"height":193,"name":"monero/binder","x":1403},{"width":311,"y":3717,"height":332,"name":"monero/top","x":374},{"width":327,"y":3075,"height":482,"name":"monero/trtlneck","x":999},{"width":413,"y":2639,"height":484,"name":"monero/skirt","x":1624},{"width":144,"y":3927,"height":122,"name":"monero/neckless","x":1218},{"width":402,"y":3559,"height":366,"name":"monero/hairfront","x":999},{"width":623,"y":2639,"height":434,"name":"monero/leftarm-righthand","x":999},{"width":187,"y":3075,"height":586,"name":"monero/jacket-right","x":1403},{"width":230,"y":3578,"height":286,"name":"monero/jacketsleeve-left","x":1737},{"width":143,"y":3125,"height":613,"name":"monero/jacket-left","x":1592},{"width":293,"y":3866,"height":202,"name":"monero/hand-left","x":1721},{"width":642,"y":2164,"height":473,"name":"monero/jacket-sleeves","x":999}]}