{"width":2048,"SubTexture":[{"width":375,"y":1459,"height":1040,"name":"bitcoin-diamond/dress-back","x":419},{"width":257,"y":1,"height":851,"name":"bitcoin-diamond/ponytail","x":752},{"width":336,"y":1,"height":438,"name":"bitcoin-diamond/fur-left","x":1011},{"width":209,"y":1118,"height":357,"name":"bitcoin-diamond/armleft","x":1338},{"width":185,"y":304,"height":473,"name":"bitcoin-diamond/handleft","x":1668},{"width":386,"y":1,"height":2316,"name":"bitcoin-diamond/body-main","x":1},{"width":174,"y":779,"height":240,"name":"bitcoin-diamond/shoeleft","x":1796},{"width":59,"y":1,"height":150,"name":"bitcoin-diamond/bracelets","x":1944},{"width":156,"y":1021,"height":53,"name":"bitcoin-diamond/eyeballs","x":1796},{"width":133,"y":304,"height":46,"name":"bitcoin-diamond/pupils","x":1349},{"width":189,"y":556,"height":111,"name":"bitcoin-diamond/eyes","x":1855},{"width":53,"y":669,"height":74,"name":"bitcoin-diamond/face","x":1968},{"width":325,"y":441,"height":386,"name":"bitcoin-diamond/chelka","x":1011},{"width":302,"y":1118,"height":222,"name":"bitcoin-diamond/boob","x":1549},{"width":318,"y":1,"height":301,"name":"bitcoin-diamond/bra","x":1349},{"width":275,"y":1342,"height":210,"name":"bitcoin-diamond/pants","x":1549},{"width":111,"y":669,"height":78,"name":"bitcoin-diamond/shoeright-2","x":1855},{"width":361,"y":1,"height":1456,"name":"bitcoin-diamond/rightleg","x":389},{"width":137,"y":267,"height":287,"name":"bitcoin-diamond/shoe-right1","x":1855},{"width":386,"y":854,"height":486,"name":"bitcoin-diamond/underdress","x":752},{"width":329,"y":1342,"height":147,"name":"bitcoin-diamond/top_underdress","x":796},{"width":416,"y":2319,"height":1748,"name":"bitcoin-diamond/dress","x":1},{"width":328,"y":441,"height":310,"name":"bitcoin-diamond/top_dress","x":1338},{"width":108,"y":267,"height":34,"name":"bitcoin-diamond/necklace","x":1669},{"width":215,"y":779,"height":294,"name":"bitcoin-diamond/armright","x":1579},{"width":141,"y":1342,"height":250,"name":"bitcoin-diamond/fur_right2","x":1127},{"width":239,"y":753,"height":363,"name":"bitcoin-diamond/hand_right","x":1338},{"width":273,"y":1,"height":264,"name":"bitcoin-diamond/fur-right1","x":1669}],"height":4096,"name":"bitcoin-diamond","imagePath":"bitcoin-diamond_tex.png"}